ReExpose-0.1.1.data/scripts/reexpose
reexpose/__init__.py
reexpose/reexpose.py
ReExpose-0.1.1.dist-info/LICENSE
ReExpose-0.1.1.dist-info/METADATA
ReExpose-0.1.1.dist-info/WHEEL
ReExpose-0.1.1.dist-info/top_level.txt
ReExpose-0.1.1.dist-info/RECORD
