Metadata-Version: 2.1
Name: ReExpose
Version: 0.1.1
Summary: ReExpose HTTP basic auth endpoints on localhost as unauthenticated endpoints
Home-page: https://github.com/jeffcasavant/reexpose
Author: Jeff Casavant
Author-email: jeff.casavant@gmail.com
License: UNKNOWN
Platform: UNKNOWN
Classifier: Programming Language :: Python :: 3
Classifier: Framework :: Flask
Classifier: Intended Audience :: Developers
Classifier: Intended Audience :: System Administrators
Classifier: License :: OSI Approved :: MIT License
Classifier: Topic :: Internet :: WWW/HTTP
Requires-Dist: cachetools
Requires-Dist: flask
Requires-Dist: gevent
Requires-Dist: requests
Requires-Dist: pyyaml
Provides-Extra: dev
Requires-Dist: pylint; extra == 'dev'
Requires-Dist: twine; extra == 'dev'
